src/__init__.py
cvar_optimization_benchmarks-0.1.2.dist-info/METADATA
cvar_optimization_benchmarks-0.1.2.dist-info/WHEEL
cvar_optimization_benchmarks-0.1.2.dist-info/LICENSE
cvar_optimization_benchmarks-0.1.2.dist-info/RECORD
